MANIFEST.in
README.rst
pyproject.toml
setup.py
adapya/__init__.py
adapya/era/scripts/inq.py
adapya/era/scripts/outq.py
adapya/era/scripts/readris.py
adapya/era/__init__.py
adapya/era/reptor.py
adapya/era/tapada.py
adapya/era/urb.py
adapya/era/doc/conf.py
adapya/era/doc/_static/image006.jpg
adapya/era/internal/__init__.py
adapya/era/internal/rcOut3Config.py
adapya/era/internal/tapa12config.py
adapya/era/internal/EmployeeReplication/__init__.py
adapya/era/internal/EmployeeReplication/rcOut1.py
adapya/era/internal/EmployeeReplication/rcOut1Config.py
adapya/era/internal/EmployeeReplication/win_iq1.cmd
adapya/era/internal/EmployeeReplication/fdt/empltel.fdt
adapya/era/internal/EmployeeReplication/fdt/win_adafdu_empltel.cmd
adapya/era/internal/fdt/emp_nat_mf_uppercase.fdt
adapya/era/internal/mq/getmsg.py
adapya/era/scripts/__init__.py
adapya/era/scripts/inq.py
adapya/era/scripts/outq.py
adapya/era/scripts/readris.py
adapya_era.egg-info/PKG-INFO
adapya_era.egg-info/SOURCES.txt
adapya_era.egg-info/dependency_links.txt
adapya_era.egg-info/namespace_packages.txt
adapya_era.egg-info/not-zip-safe
adapya_era.egg-info/requires.txt
adapya_era.egg-info/top_level.txt